{
  "1.0.0": {
    "all": {
      "show": false,
      "title": "Outdated version",
      "message": "Please update to the latest version of the application.",
      "type": "warning"
    }
  },
  "1.1.0": {
    "all": {
      "show": false,
      "title": "Outdated version",
      "message": "Please update to the latest version of the application.",
      "type": "warning"
    }
  },
  "1.2.0": {
    "all": {
      "show": false,
      "title": "Outdated version",
      "message": "Please update to the latest version of the application.",
      "type": "warning"
    }
  },
  "1.3.0": {
    "linux": {
      "show": false,
      "title": "Outdated version",
      "message": "Please update to the latest version of the application.",
      "type": "warning"
    },
    "win32": {
      "show": false,
      "title": "Outdated version",
      "message": "Please update to the latest version of the application.",
      "type": "warning"
    },
    "darwin": {
      "show": false,
      "title": "Outdated version",
      "message": "Please update to the latest version of the application.",
      "type": "warning"
    }
  },
  "1.4.0": {
    "darwin": {
      "show": true,
      "title": "Outdated version",
      "message": "Please update to the latest version of the application.",
      "type": "warning"
    }
  }
}
